marlben/__init__.py
marlben/infrastructure.py
marlben/overlay.py
marlben/scripting.py
marlben/version.py
marlben/websocket.py
marlben/config/__init__.py
marlben/config/builders.py
marlben/config/common.py
marlben/config/presets.py
marlben/config/base/__init__.py
marlben/config/base/config.py
marlben/config/base/presets.py
marlben/config/systems/__init__.py
marlben/config/systems/config.py
marlben/config/systems/presets.py
marlben/core/__init__.py
marlben/core/agent.py
marlben/core/env.py
marlben/core/map.py
marlben/core/realm.py
marlben/core/tile.py
marlben/core/map_generation/__init__.py
marlben/core/map_generation/base.py
marlben/core/map_generation/checks.py
marlben/core/map_generation/pregen_map_generator.py
marlben/core/map_generation/resources.py
marlben/core/map_generation/rock_patterns.py
marlben/core/spawn/__init__.py
marlben/core/spawn/base_manager.py
marlben/core/spawn/spawn_system/__init__.py
marlben/core/spawn/spawn_system/base.py
marlben/core/spawn/spawn_system/base_samplers.py
marlben/core/spawn/spawn_system/position_samplers.py
marlben/core/spawn/spawn_system/skill_samplers.py
marlben/entity/__init__.py
marlben/entity/entity.py
marlben/entity/npc.py
marlben/entity/player.py
marlben/envs/__init__.py
marlben/envs/arena/__init__.py
marlben/envs/arena/config.py
marlben/envs/arena/env.py
marlben/envs/arena/test_maps/maps.json
marlben/envs/boss_fight/__init__.py
marlben/envs/boss_fight/config.py
marlben/envs/boss_fight/env.py
marlben/envs/boss_fight/maps/maps.json
marlben/envs/building/__init__.py
marlben/envs/building/config.py
marlben/envs/building/env.py
marlben/envs/building/test_maps/maps.json
marlben/envs/colors/__init__.py
marlben/envs/colors/config.py
marlben/envs/colors/env.py
marlben/envs/corridor/__init__.py
marlben/envs/corridor/config.py
marlben/envs/corridor/env.py
marlben/envs/corridor/maps/maps.json
marlben/envs/deathmatch/__init__.py
marlben/envs/deathmatch/config.py
marlben/envs/deathmatch/env.py
marlben-1.0.4.dist-info/LICENSE
marlben-1.0.4.dist-info/METADATA
marlben-1.0.4.dist-info/WHEEL
marlben-1.0.4.dist-info/top_level.txt
marlben-1.0.4.dist-info/RECORD
